setup.py
bipolar/__init__.py
bipolar/client.py
bipolar/version.py
bipolar_client.egg-info/PKG-INFO
bipolar_client.egg-info/SOURCES.txt
bipolar_client.egg-info/dependency_links.txt
bipolar_client.egg-info/requires.txt
bipolar_client.egg-info/top_level.txt
tests/__init__.py
tests/unit.py