Metadata-Version: 1.1
Name: bipolar-client
Version: 0.1.2
Summary: Bipolar client
Home-page: http://github.com/marinho/bipolar-python-client/
Author: Marinho Brandao
Author-email: marinho@gmail.com
License: BSD
Keywords: python bipolar feature toggle switch
Platform: UNKNOWN
Classifier: Development Status :: 4 - Beta
Classifier: Intended Audience :: Developers
Classifier: License :: OSI Approved :: MIT License
Classifier: Natural Language :: English
Classifier: Operating System :: MacOS
Classifier: Operating System :: POSIX
Classifier: Operating System :: Unix
Classifier: Operating System :: OS Independent
Classifier: Programming Language :: Python :: 2.7
